{
  "form__name": "BCA-BR-PFI",
  "form__last_update_date": "",
  "form__create_date": "",
  "form__version": "1.0",
  "FormName10": "",
  "XFDVersion": "",
  "agencyUrl10": {
    "url": "https://bcaisps:443/rest/validatePfiReference",
    "params": "psiReference=",
    "body": {}
  },
  "Date10": "",
  "Addr10": "Building and Construction Authority",
  "Addr20": "Commissioner of Building Control\nBuilding and Construction Authority\n52 Jurong Gateway Road, #11-01\nSingapore 608550",
  "App_Type_Comp_Person10": true,
  "App_Type_Facade_Insp_Cert10": false,
  "App_Type_Facade_Inv_Cert10": false,
  "App_Type_Cert_Repairs10": false,
  "PartOfBuil_NotiRefeNo10": "",
  "PartOfBuil_NotiRefeNo20": "",
  "PartOfBuil_NotiRefeNo30": "",
  "PartOfBuil_Buil_Address10": "",
  "PartOfBuil_BP_ST_No10": "",
  "PartOfBuil_BP_ST_field10": "",
  "PartOfBuil_Lot_Mukim_No10": "",
  "PartOfBuil_Lot_Mukim_field10": "",
  "PartOfOwner_Member_Name10": "",
  "PartOfOwner_Member_Owner10": true,
  "PartOfOwner_Member_MCST10": false,
  "PartOfOwner_Member_MCST_No10": "",
  "PartOfOwner_Member_Firm_Name10": "",
  "PartOfOwner_Member_UEN10": "",
  "PartOfOwner_Member_Address10": "",
  "PartOfOwner_Member_Tele_No10": "",
  "PartOfOwner_Member_Hand_No10": "",
  "PartOfOwner_Member_Email_Add10": "",
  "Decl_Owner_Appo_Comp_Pers_Chkbx10": "",
  "Decl_Owner_Role10": "",
  "Decl_Owner_Faca_Buil_Type10": "",
  "Decl_Owner_Role20": "",
  "Decl_Owner_Faca_Buil_Type20": "",
  "Decl_Owner_Auth_Comp_Pers_Chkbx10": "",
  "PartOfQualPers_Name10": "",
  "PartOfQualPers_Regi_No10": "",
  "PartOfQualPers_Arch10": "",
  "PartOfQualPers_Prof_Eng10": "",
  "PartOfQualPers_Firm_Name10": "",
  "PartOfQualPers_UEN10": "",
  "PartOfQualPers_Add10": "",
  "PartOfQualPers_Hand_No10": "",
  "PartOfQualPers_Email_Add10": "",
  "ConfOfApp_Role10": "",
  "ConfOfApp_App_Pers_Chkbox10": "",
  "ConfOfAppRole_Name10": "",
  "ConfOfApp_Faca_Buil_Type10": "",
  "ConfOfApp_Faca_Buil_Type_Chkbox10": "",
  "ConfOfApp_Faca_Buil_Type20": "",
  "ConfOfApp_Role_Name20": "",
  "ConfOfApp_Decl_Chkbox10": "",
  "DeclOfQualPers_Role10": "",
  "DeclOfQualPers_Role_field10": "",
  "DeclOfQualPers_To_Date10": "",
  "DeclOfQualPers_From_Date10": "",
  "DeclOfQualPers_Chkbox10": false,
  "DeclOfQualPers_Chkbox20": false,
  "DeclOfQP_Type_Buil_Resi10": false,
  "DeclOfQP_Type_Buil_Comm10": false,
  "DeclOfQP_Type_Buil_Indu10": false,
  "DeclOfQP_Type_Buil_Inst10": false,
  "DeclOfQP_Type_Buil_Others10": false,
  "DeclOfQP_Type_Buil_Others_field10": "",
  "DeclOfQP_Buil_Deta_Date_TOP10": "",
  "DeclOfQP_Buil_Deta_Age10": "",
  "DeclOfQP_Buil_Deta_Date_PSI10": "",
  "DeclOfQP_Buil_Deta_No_Buildings10": "",
  "DeclOfQP_Buil_Deta_No_Storeys10": "",
  "DeclOfQP_Buil_Deta_Height_Buil10": "",
  "DeclOfQP_Type_Faca_Curt_Wall_with_SSG10": false,
  "DeclOfQP_Type_Faca_Curt_Wall_wo_SSG10": false,
  "DeclOfQP_Type_Faca_Clad10": false,
  "DeclOfQP_Type_Faca_Comp_Alum_Clad10": false,
  "DeclOfQP_Type_Faca_Meta_Clad_wo_ACP10": false,
  "DeclOfQP_Type_Faca_Buil_Boar_Clad10": false,
  "DeclOfQP_Type_Faca_BricClad10": false,
  "DeclOfQP_Type_Faca_TimbClad10": false,
  "DeclOfQP_Type_Faca_StonClad10": false,
  "DeclOfQP_Type_Faca_BricInfi_Wall10": false,
  "DeclOfQP_Type_Faca_GlasBlocInfi_Wall10": false,
  "DeclOfQP_Type_Faca_Prec_Conc_Wall10": false,
  "DeclOfQP_Type_Faca_Scre_Wall10": false,
  "DeclOfQP_Type_Faca_Gree_Wall10": false,
  "DeclOfQP_Type_Faca_Tens_Cabl_Faca10": false,
  "DeclOfQP_Type_Faca_Others10": false,
  "DeclOfQP_Type_Faca_Others_field10": "",
  "DeclOfQP_Type_Atta_Meta_Suns10": false,
  "DeclOfQP_Type_Atta_Suns10": false,
  "DeclOfQP_Type_Atta_Fin10": false,
  "DeclOfQP_Type_Atta_Meta_Louv10": false,
  "DeclOfQP_Type_Atta_Glas_Louv10": false,
  "DeclOfQP_Type_Atta_Conc_Louv10": false,
  "DeclOfQP_Type_Atta_Conc_Fin10": false,
  "DeclOfQP_Type_Atta_Meta_Fin10": false,
  "DeclOfQP_Type_Atta_Glas_Fin10": false,
  "DeclOfQP_Type_Atta_AdveSign10": false,
  "DeclOfQP_Type_Atta_Clot_Dryi_Rack10": false,
  "DeclOfQP_Type_Atta_Phot_Pane10": false,
  "DeclOfQP_Type_Atta_Others10": false,
  "DeclOfQP_Type_Atta_Others_field10": "",
  "DeclOfQP_Type_Faca_Chkbox10": false,
  "DeclOfQP_Safe10": "",
  "DeclOfQP_Require_Repa10": "",
  "DeclOfQP_Unsafe10": "",
  "DeclOfQP_ReqFaca_Inves10": "",
  "DeclOfQP_Chkbox30": false,
  "DeclOfQP_Deta_Facade_Insp_Name10": "",
  "DeclOfQP_Deta_Facade_Insp_FI_RegNo10": "",
  "DeclOfQP_Deta_Facade_Insp_Hand_No10": "",
  "DeclOfQP_Chkbox40": false,
  "DeclOfQP_Role_Name10": "",
  "DeclOfQP_Chkbox50": false,
  "DeclOfQP_Role10": "",
  "DeclOfQP_Role_field10": "",
  "DeclOfQP_From_Date10": "",
  "DeclOfQP_To_Date10": "",
  "DeclOfQP_Chkbox60": false,
  "DeclOfQP_Deta_Facade_Invs_Name10": "",
  "DeclOfQP_Deta_Facade_Invs_FI_RegNo10": "",
  "DeclOfQP_Deta_Facade_Invs_Hand_No10": "",
  "DeclOfQP_Inves_Require_Repa10": "",
  "DeclOfQP_Inves_Unsafe10": "",
  "DeclOfQP_Chkbox70": false,
  "DeclOfQP_Chkbox90": false,
  "DeclOfQP_Chkbox80": false,
  "DeclOfQP_Role_Name20": "",
  "DeclOfQP_Role20": "",
  "DeclOfQP_Role_Field20": "",
  "DeclOfQP_From_Date20": "",
  "DeclOfQP_To_Date20": "",
  "DeclOfQP_Chkbox100": false,
  "DeclOfQP_Report_Date10": "",
  "ProjectAddress_Building_Name10": "",
  "DeclOfQP_Buil_Deta_Building10": "",
  "DeclOfQP_Type_Faca_Tile10": false,
  "DeclOfQP_Type_Plas10": false,
  "DeclOfQP_Buil_Deta_Date_NA_PSI10": false
}
