{
    "form__name": "LTA-DBC_VEHICLE PARKING",
    "form__last_update_date": "",
    "form__create_date": "",
    "form__version": "1.0",
    "Date10": "30/09/2020",
    "Addr10": "Land Transport Authority (LTA)",
    "Addr20": "Development & Building Control\n251 North Bridge Road\nSingapore 179102",
    "ApplType_VPBldgPlan": true,
    "ApplType_VPLodgeVP": false,
    "ApplType_VPCertStaComp": false,
    "ApplType_VPModDim": false,
    "ApplType_VPWaiver": false,
    "Project_Project_Ref_No10": "",
    "Building_Plan_Ref_No10": "",
    "Project_Title10": "",
    "POPUP3": "",
    "RDLotNo_110": "MK",
    "RDLotNo_210": "",
    "RDLotNo_310": "",
    "RDLotNo_410": "",
    "RDLotNo_510": "Full",
    "Project_StreName10": "",
    "DeveSubType_FIELD1": "",
    "DeveSubType_FIELD2": "",
    "DeveSubType_FIELD3": "",
    "SubType_NewSub10": true,
    "SubType_Resub10": false,
    "DeveSubType_CHECK1": false,
    "DeveSubType_CHECK21": false,
    "DeveSubType_CHECK2": false,
    "DeveSubType_CHECK23": false,
    "DeveSubType_CHECK24": false,
    "DeveSubType_CHECK15": false,
    "DeveSubType_CHECK25": false,
    "DeveSubType_CHECK20": false,
    "DeveSubType_CHECK22": false,
    "Project_BIMYES10": false,
    "Project_BIMNO10": false,
    "Member_Member_Name_QP10": "1",
    "VPPRO_CHECKSD10": "",
    "VPPRO_CHECK1": false,
    "VPPRO_CHECK2_1": false,
    "VPPRO_CHECK2_2": false,
    "VPPRO_CHECK2_3": false,
    "VPPRO_CHECK2_4": false,
    "VPPRO_CHECK3": false,
    "VPPRO_CHECK4": true,
    "VPPRO_GFA10": "12331.00",
    "VPPRO_QtyGfa10": "",
    "VPPRO_CompFees10": "",
    "VPPRO_NewSubm10": false,
    "VPPRO_NewSubm_Amount20": "",
    "VPPRO_NewSubm_ReceNo10": "",
    "VPPRO_Resu10": false,
    "VPPRO_Resu_FullPaymDoneEarl10": false,
    "VPPRO_Resu_SubmNoFeePaid10": "",
    "VPPRO_Resu_TopUpPaymDone10": false,
    "VPPRO_Resu_Amount20": "",
    "VPPRO_Resu_ReceNo10": "",
    "VPPRO_Rema10": "",
    "VPLOD_CHECK1": false,
    "VPLOD_CHECK2": false,
    "VPLOD_CHECK3": false,
    "VPLOD_CHECK4": false,
    "VPLOD_CHECK5_1": false,
    "VPLOD_CHECK5_2": false,
    "VPLOD_CHECK5_3": false,
    "VPLOD_CHECK5_4": false,
    "VPLOD_CHECK5_5": false,
    "VPLOD_CHECK6": false,
    "VPLOD_ReceNum10": "",
    "VPLOD_Amount10": "",
    "VPLOD_QtyGfa10": "",
    "VPLOD_CompFees10": "",
    "VPLOD_NewSubm10": false,
    "VPLOD_NewSubm_Amount20": "",
    "VPLOD_NewSubm_ReceNo10": "",
    "VPLOD_Resu10": false,
    "VPLOD_Resu_FullPaymDoneEarl10": false,
    "VPLOD_Resu_SubmNoFeePaid10": "",
    "VPLOD_Resu_TopUpPaymDone10": false,
    "VPLOD_Resu_Amount20": "",
    "VPLOD_Resu_ReceNo10": "",
    "VPLOD_Rema10": "",
    "VPCSC_CHECKSD10": "",
    "VPCSC_CHECK1": false,
    "WithNoDevi10": false,
    "WithDevi10": false,
    "VPCSC_CHECK2": false,
    "TheDeviConf10": false,
    "TheDeviDoesNot10": false,
    "VPCSC_CHECK3_1": false,
    "VPCSC_CHECK3_2": false,
    "VPCSC_CHECK3_3": false,
    "VPCSC_CHECK4": false,
    "VPCSC_Rema10": "",
    "VPMODDIM_CHECKSD10": "",
    "VPMODDIM_CHECK1": false,
    "VPMODDIM_CHECK2_1": false,
    "VPMODDIM_CHECK2_2": false,
    "VPMODDIM_CHECK2_3": false,
    "VPMODDIM_CHECK3": false,
    "VPMODDIM_GFA10": "",
    "VPMODDIM_ReceNum10": "",
    "VPMODDIM_Amount10": "",
    "VPMODDIM_QtyGfa10": "",
    "VPMODDIM_CompFees10": "",
    "VPMODDIM_NewSubm10": false,
    "VPMODDIM_NewSubm_Amount20": "",
    "VPMODDIM_NewSubm_ReceNo10": "",
    "VPMODDIM_Resu10": false,
    "VPMODDIM_Resu_FullPaymDoneEarl10": false,
    "VPMODDIM_Resu_SubmNoFeePaid10": "",
    "VPMODDIM_Resu_TopUpPaymDone10": false,
    "VPMODDIM_Resu_Amount20": "",
    "VPMODDIM_Resu_ReceNo10": "",
    "VPMODDIM_Rema10": "",
    "VPWAI_CHECKSD10": "",
    "VPWAI_CHECK1": false,
    "VPWAI_CHECK2_1": false,
    "VPWAI_CHECK2_2": false,
    "VPWAI_CHECK2_3": false,
    "VPWAI_GFA10": "",
    "VPWAI_CHECK3": false,
    "VPWAI_ReceNum10": "",
    "VPWAI_Amount10": "",
    "VPWAI_QtyGfa10": "",
    "VPWAI_CompFees10": "",
    "VPWAI_NewSubm10": false,
    "VPWAI_NewSubm_Amount20": "",
    "VPWAI_NewSubm_ReceNo10": "",
    "VPWAI_Resu10": false,
    "VPWAI_Resu_FullPaymDoneEarl10": false,
    "VPWAI_Resu_SubmNoFeePaid10": "",
    "VPWAI_Resu_TopUpPaymDone10": false,
    "VPWAI_Resu_Amount20": "",
    "VPWAI_Resu_ReceNo10": "",
    "VPWAI_Rema10": "",
    "VPLOD_GFA10": "",
    "StatBoar_Yes10": false,
    "StatBoar_No10": true,
    "senderDropdown": [
        {
            "Member_Member_Name_QP10": ""
        }
    ]
}